sqam/__init__.py
sqam/app.py
SQAM-0.1.0.dist-info/METADATA
SQAM-0.1.0.dist-info/WHEEL
SQAM-0.1.0.dist-info/entry_points.txt
SQAM-0.1.0.dist-info/top_level.txt
SQAM-0.1.0.dist-info/RECORD
