Metadata-Version: 2.1
Name: SQAM
Version: 0.1.0
Summary: Simplified Question Answering Machine
Home-page: https://github.com/preslaff/SQAM
Author: preslaff
Author-email: preslaff@gmail.com
Classifier: Programming Language :: Python :: 3
Classifier: License :: OSI Approved :: MIT License
Classifier: Operating System :: OS Independent
Requires-Python: >=3.6
Requires-Dist: Flask
Requires-Dist: numpy
Requires-Dist: sentence-transformers
Requires-Dist: scikit-learn
Requires-Dist: pytest
